{
  "hash": "951b0509",
  "browserHash": "a4aabaee",
  "optimized": {
    "vue": {
      "src": "../../../../node_modules/vue/dist/vue.runtime.esm-bundler.js",
      "file": "vue.js",
      "fileHash": "e2ea1b14",
      "needsInterop": false
    },
    "@theme/index": {
      "src": "../../../../node_modules/vitepress/dist/client/theme-default/index.js",
      "file": "@theme_index.js",
      "fileHash": "42d0ef54",
      "needsInterop": false
    },
    "imask": {
      "src": "../../../../node_modules/imask/esm/index.js",
      "file": "imask.js",
      "fileHash": "50bfadeb",
      "needsInterop": false
    },
    "@vueuse/core": {
      "src": "../../../../node_modules/@vueuse/core/index.mjs",
      "file": "@vueuse_core.js",
      "fileHash": "2d21629d",
      "needsInterop": false
    },
    "libphonenumber-js": {
      "src": "../../../../node_modules/libphonenumber-js/index.js",
      "file": "libphonenumber-js.js",
      "fileHash": "a2b058d7",
      "needsInterop": false
    },
    "libphonenumber-js/examples.mobile.json": {
      "src": "../../../../node_modules/libphonenumber-js/examples.mobile.json.js",
      "file": "libphonenumber-js_examples__mobile__json.js",
      "fileHash": "83cab459",
      "needsInterop": false
    }
  },
  "chunks": {
    "chunk-6S52NMOK": {
      "file": "chunk-6S52NMOK.js"
    }
  }
}